nlpbridge/__init__.py
nlpbridge/nlp.py
nlpbridge/audio/__init__.py
nlpbridge/audio/_client.py
nlpbridge/audio/_exception.py
nlpbridge/audio/component.py
nlpbridge/audio/message.py
nlpbridge/audio/components/__init__.py
nlpbridge/audio/components/asr/__init__.py
nlpbridge/audio/components/asr/asr.py
nlpbridge/audio/components/asr/model.py
nlpbridge/audio/components/tts/__init__.py
nlpbridge/audio/components/tts/model.py
nlpbridge/audio/components/tts/tts.py
nlpbridge/audio/utils/__init__.py
nlpbridge/audio/utils/logger_util.py
nlpbridge/langchain_zhipuai/__init__.py
nlpbridge/langchain_zhipuai/embeddings/__init__.py
nlpbridge/langchain_zhipuai/embeddings/base.py
nlpbridge/persistent/__init__.py
nlpbridge/persistent/persistent_store.py
nlpbridge/persistent/redis.py
nlpbridge/text/__init__.py
nlpbridge/text/agent.py
nlpbridge/text/graph.py
nlpbridge/text/memory.py
nlpbridge/text/models.py
nlpbridge/text/template_manager.py
nlpbridge/text/tools.py
tests/__init__.py
tests/audio/__init__.py
tests/audio/clients.py
tests/audio/interface_demo.py
tests/audio/backend/__init__.py
tests/audio/backend/api.py
tests/audio/backend/config.py
tests/audio/backend/main.py
tests/audio/backend/audio/__init__.py
tests/audio/backend/audio/asr.py
tests/audio/backend/audio/asrStream.py
tests/audio/backend/audio/tts-client-fix.py
tests/audio/backend/audio/tts-client.py
tests/audio/backend/audio/tts.py
tests/text/__init__.py
tests/text/test_FINAL.py
tests/text/test_agent.py
tests/text/test_agent_RAG.py
tests/text/test_agent_executor.py
tests/text/test_agent_with_memory.py
tests/text/test_chain.py
tests/text/test_graph.py
tests/text/test_happyagent.py
tests/text/test_memory.py
tests/text/test_nlp.py
tests/text/test_pickle.py
tests/text/test_redis.py
tests/text/test_template.py
tests/text/test_template_getter.py
midplugin-0.1.0.dist-info/LICENSE
midplugin-0.1.0.dist-info/METADATA
midplugin-0.1.0.dist-info/WHEEL
midplugin-0.1.0.dist-info/entry_points.txt
midplugin-0.1.0.dist-info/top_level.txt
midplugin-0.1.0.dist-info/RECORD
