Metadata-Version: 2.1
Name: midplugin
Version: 0.1.0
Summary: NLPBridge
Home-page: https://github.com/GZU4AI/nlpbridge/tree/vitalis
Author: vitalis
Author-email: vitalis.free@gmail.com
License: MIT
Classifier: Programming Language :: Python :: 3
Classifier: License :: OSI Approved :: MIT License
Classifier: Operating System :: OS Independent
Requires-Python: >=3.6
License-File: LICENSE
Requires-Dist: langchain
Requires-Dist: langchain-community
Requires-Dist: langgraph
